cmmparsers/DbDumpParser.py
cmmparsers/RedisDumpParser.py
cmmparsers/__init__.py
cmmparser_aemillius-0.0.3.dist-info/LICENSE
cmmparser_aemillius-0.0.3.dist-info/METADATA
cmmparser_aemillius-0.0.3.dist-info/WHEEL
cmmparser_aemillius-0.0.3.dist-info/top_level.txt
cmmparser_aemillius-0.0.3.dist-info/RECORD
