Metadata-Version: 2.1
Name: cmmparser-aemillius
Version: 0.0.3
Summary: parsers for node dump
Home-page: https://github.com/aemillius/cmmparser1
Author: Rajender Singh
Author-email: rajranasingh@rediffmail.com
License: UNKNOWN
Platform: UNKNOWN
Classifier: Programming Language :: Python :: 3
Classifier: License :: OSI Approved :: MIT License
Classifier: Operating System :: OS Independent
Requires-Python: >=3.6
